library/__init__.py
library/algosec_add_single_application_flow.py
library/algosec_define_application_flows.py
library/algosec_provision_network_connectivity.py
ansible_role_algosec-0.6.0.dist-info/LICENSE
ansible_role_algosec-0.6.0.dist-info/METADATA
ansible_role_algosec-0.6.0.dist-info/WHEEL
ansible_role_algosec-0.6.0.dist-info/top_level.txt
ansible_role_algosec-0.6.0.dist-info/RECORD
