Metadata-Version: 2.1
Name: ansible-role-algosec
Version: 0.6.0
Summary: Set of Ansible modules for AlgoSec services management
Home-page: https://github.com/AlmogCohen/ansible-role-algosec
Author: Almog Cohen
Author-email: UNKNOWN
License: MIT
Platform: UNKNOWN
Classifier: Development Status :: 4 - Beta
Classifier: Intended Audience :: Developers
Classifier: Intended Audience :: Information Technology
Classifier: License :: OSI Approved :: MIT License
Classifier: Natural Language :: English
Classifier: Topic :: Software Development :: Libraries :: Python Modules
Classifier: Programming Language :: Python :: 2.7
Classifier: Programming Language :: Python :: 3.6
Requires-Dist: algosec (>=1.3.1)
Requires-Dist: ansible
Requires-Dist: marshmallow
Requires-Dist: urllib3
